leanquant/__init__.py
leanquant/leanquant_utils.py
leanquant-0.1.1.dist-info/LICENSE
leanquant-0.1.1.dist-info/METADATA
leanquant-0.1.1.dist-info/WHEEL
leanquant-0.1.1.dist-info/top_level.txt
leanquant-0.1.1.dist-info/RECORD
