Metadata-Version: 2.2
Name: leanquant
Version: 0.1.1
Summary: The inference kernels for LeanQuant models.
Author: Tianyi Zhang
Author-email: tonyzhang617@gmail.com
License-File: LICENSE
Requires-Dist: transformers>=4.38
Requires-Dist: accelerate
Requires-Dist: safetensors
Requires-Dist: torch
Provides-Extra: cuda11
Requires-Dist: cupy-cuda11x; extra == "cuda11"
Provides-Extra: cuda12
Requires-Dist: cupy-cuda12x; extra == "cuda12"
Dynamic: author
Dynamic: author-email
Dynamic: description
Dynamic: description-content-type
Dynamic: provides-extra
Dynamic: requires-dist
Dynamic: summary
